LICENSE
README
ez_setup.py
install.bat
setup.py
install/README
install/soap_meetings.php
install/soap_users.php
pysugar/__init__.py
pysugar/pysugar.py
pysugar/pysugar_version.py
pysugar/sugarobjects.py
pysugar/sugarstore.py
pysugarNG.egg-info/PKG-INFO
pysugarNG.egg-info/SOURCES.txt
pysugarNG.egg-info/dependency_links.txt
pysugarNG.egg-info/not-zip-safe
pysugarNG.egg-info/requires.txt
pysugarNG.egg-info/top_level.txt