Metadata-Version: 1.0
Name: pysugarNG
Version: 0.0.7
Summary: Fork of Python binding of SugarCRM, that uses the SOAP API provided by SugarCRM
Home-page: UNKNOWN
Author: Mathieu PASQUET <kiorky@cryptelium.net>, Florent Aide, Christophe de Vienne
Author-email: florent.aide@gmail.com, cdevienne@alphacent.com, Mathieu PASQUET <kiorky@cryptelium.net>
License: PSF
Keywords: Sugar CRM SOAP
Platform: UNKNOWN
